drf_body_token/__init__.py
drf_body_token/authentication.py
drf_body_token-0.1.0.dist-info/LICENSE
drf_body_token-0.1.0.dist-info/WHEEL
drf_body_token-0.1.0.dist-info/METADATA
drf_body_token-0.1.0.dist-info/RECORD
